{
   "Ads":[
      {
         "select_main_ads":"ADMOB",
         "select_backup_ads":"null",
         "main_ads_banner":"ca-app-pub-3940256099942544/6300978111x",
         "main_ads_intertitial":"ca-app-pub-3940256099942544/1033173712x",
         "main_ads_natives":"",
         "main_ads_rewards":"",
         "backup_ads_natives":"",
         "backup_ads_banner":"",
         "backup_ads_intertitial":"",
         "backup_ads_rewards":"",
         "open_ads_admob":"",
         "open_ads_alien":"",
         "switch_open_ads":"1",
         "switch_banner_natives_ads":"1",
         "on_off_native_listview":"0",
         "interval_intertitial":5,
         "initialize_sdk":"",
         "initialize_sdk_backup_ads":"",
         "high_paying_keyword_1":"",
         "high_paying_keyword_2":"",
         "high_paying_keyword_3":"",
         "high_paying_keyword_4":"",
         "high_paying_keyword_5":"",
         "status_app":"0",
         "link_redirect":"https://",
         "on_off_category":""
      }
   ],
   "More":[
      {
         "id":1,
         "title":"Ceiling Design for Bedroom",
         "image":"https://keybpopcode.files.wordpress.com/2023/01/ceiling-design-for-bedroom-icon.png",
         "link":"https://play.google.com/store/apps/details?id=com.keybpop.niceceilingdesignforbedroomhome"
      }
   ],
   "Categories":[
      {
         "id":1,
         "name_category":"Back Blouse Design",
         "image":"https://keybpopcode.files.wordpress.com/2023/01/backblouse001.jpg"
      }
   ],
   "Data":[
      {
         "id":1,
         "name_category":"Back Blouse Design",
         "title":"Back Blouse Design 1",
         "image":"https://keybpopcode.files.wordpress.com/2023/01/backblouse001.jpg"
      },
      {
         "id":2,
         "name_category":"Back Blouse Design",
         "title":"Back Blouse Design 2",
         "image":"https://keybpopcode.files.wordpress.com/2023/01/backblouse002.jpg"
      },
      {
         "id":3,
         "name_category":"Back Blouse Design",
         "title":"Back Blouse Design 3",
         "image":"https://keybpopcode.files.wordpress.com/2023/01/backblouse003.jpg"
      },
      {
         "id":4,
         "name_category":"Back Blouse Design",
         "title":"Back Blouse Design 4",
         "image":"https://keybpopcode.files.wordpress.com/2023/01/backblouse004.jpg"
      },
      {
         "id":5,
         "name_category":"Back Blouse Design",
         "title":"Back Blouse Design 5",
         "image":"https://keybpopcode.files.wordpress.com/2023/01/backblouse005.jpg"
      },
      {
         "id":6,
         "name_category":"Back Blouse Design",
         "title":"Back Blouse Design 6",
         "image":"https://keybpopcode.files.wordpress.com/2023/01/backblouse006.jpg"
      },
      {
         "id":7,
         "name_category":"Back Blouse Design",
         "title":"Back Blouse Design 7",
         "image":"https://keybpopcode.files.wordpress.com/2023/01/backblouse007.jpg"
      },
      {
         "id":8,
         "name_category":"Back Blouse Design",
         "title":"Back Blouse Design 8",
         "image":"https://keybpopcode.files.wordpress.com/2023/01/backblouse008.jpg"
      },
      {
         "id":9,
         "name_category":"Back Blouse Design",
         "title":"Back Blouse Design 9",
         "image":"https://keybpopcode.files.wordpress.com/2023/01/backblouse009.jpg"
      },
      {
         "id":10,
         "name_category":"Back Blouse Design",
         "title":"Back Blouse Design 10",
         "image":"https://keybpopcode.files.wordpress.com/2023/01/backblouse010.jpg"
      },
      {
         "id":11,
         "name_category":"Back Blouse Design",
         "title":"Back Blouse Design 11",
         "image":"https://keybpopcode.files.wordpress.com/2023/01/backblouse011.jpg"
      },
      {
         "id":12,
         "name_category":"Back Blouse Design",
         "title":"Back Blouse Design 12",
         "image":"https://keybpopcode.files.wordpress.com/2023/01/backblouse012.jpg"
      },
      {
         "id":13,
         "name_category":"Back Blouse Design",
         "title":"Back Blouse Design 13",
         "image":"https://keybpopcode.files.wordpress.com/2023/01/backblouse013.jpg"
      },
      {
         "id":14,
         "name_category":"Back Blouse Design",
         "title":"Back Blouse Design 14",
         "image":"https://keybpopcode.files.wordpress.com/2023/01/backblouse014.jpg"
      },
      {
         "id":15,
         "name_category":"Back Blouse Design",
         "title":"Back Blouse Design 15",
         "image":"https://keybpopcode.files.wordpress.com/2023/01/backblouse015.jpg"
      },
      {
         "id":16,
         "name_category":"Back Blouse Design",
         "title":"Back Blouse Design 16",
         "image":"https://keybpopcode.files.wordpress.com/2023/01/backblouse016.jpg"
      },
      {
         "id":17,
         "name_category":"Back Blouse Design",
         "title":"Back Blouse Design 17",
         "image":"https://keybpopcode.files.wordpress.com/2023/01/backblouse017.jpg"
      },
      {
         "id":18,
         "name_category":"Back Blouse Design",
         "title":"Back Blouse Design 18",
         "image":"https://keybpopcode.files.wordpress.com/2023/01/backblouse018.jpg"
      },
      {
         "id":19,
         "name_category":"Back Blouse Design",
         "title":"Back Blouse Design 19",
         "image":"https://keybpopcode.files.wordpress.com/2023/01/backblouse019.jpg"
      },
      {
         "id":20,
         "name_category":"Back Blouse Design",
         "title":"Back Blouse Design 20",
         "image":"https://keybpopcode.files.wordpress.com/2023/01/backblouse020.jpg"
      },
      {
         "id":21,
         "name_category":"Back Blouse Design",
         "title":"Back Blouse Design 21",
         "image":"https://keybpopcode.files.wordpress.com/2023/01/backblouse021.jpg"
      },
      {
         "id":22,
         "name_category":"Back Blouse Design",
         "title":"Back Blouse Design 22",
         "image":"https://keybpopcode.files.wordpress.com/2023/01/backblouse022.jpg"
      }
   ]
}
